MANIFEST.in
setup.cfg
setup.py
ak_vendor/__init__.py
ak_vendor/constants.py
ak_vendor/enums.py
ak_vendor/googleplay_pb2.py
ak_vendor/pnguncrush.py
ak_vendor/report.html
ak_vendor/report.py
ak_vendor/seed.py
ak_vendor/utils.py
ak_vendoroo.egg-info/PKG-INFO
ak_vendoroo.egg-info/SOURCES.txt
ak_vendoroo.egg-info/dependency_links.txt
ak_vendoroo.egg-info/requires.txt
ak_vendoroo.egg-info/top_level.txt
data/report.html