Metadata-Version: 1.1
Name: ak-vendoroo
Version: 1.9.7
Summary: Some vendor scripts that we use here at Appknox
Home-page: https://github.com/appknox/vendor
Author: dhilipsiva
Author-email: dhilipsiva@gmail.com
License: MIT
Keywords: appknox vendor
Platform: UNKNOWN
Classifier: Development Status :: 4 - Beta
Classifier: Intended Audience :: Developers
Classifier: Topic :: Software Development :: Build Tools
Classifier: License :: OSI Approved :: MIT License
Classifier: Programming Language :: Python :: 3
Classifier: Programming Language :: Python :: 3.5
